LICENSE
MANIFEST.in
README.md
pyproject.toml
setup.py
src/jazzit/__init__.py
src/jazzit/jazz.py
src/jazzit/utils.py
src/jazzit.egg-info/PKG-INFO
src/jazzit.egg-info/SOURCES.txt
src/jazzit.egg-info/dependency_links.txt
src/jazzit.egg-info/requires.txt
src/jazzit.egg-info/top_level.txt
src/jazzit/jupyter/__init__.py
src/jazzit/jupyter/magic.py
src/jazzit/jupyter/player.py
src/jazzit/tracks/anime-wow.mp3
src/jazzit/tracks/bruh.mp3
src/jazzit/tracks/curb_your_enthusiasm.mp3
src/jazzit/tracks/elevator.mp3