Metadata-Version: 2.1
Name: jazzit
Version: 0.3.1
Summary: Add unwanted jazz to your scripts
Home-page: https://github.com/sangarshanan/jazzit
Author: sangarshanan
License: Apache 2.0
Platform: UNKNOWN
Classifier: Environment :: Console
Classifier: Programming Language :: Python
Classifier: Intended Audience :: Developers
Requires-Python: >=3.6
